{
  "kind": "collectionType",
  "collectionName": "page_templates",
  "info": {
    "singularName": "page-template",
    "pluralName": "page-templates",
    "displayName": "Page Template",
    "description": ""
  },
  "options": {
    "draftAndPublish": true
  },
  "pluginOptions": {},
  "attributes": {
    "title": {
      "type": "string"
    },
    "sections": {
      "type": "dynamiczone",
      "components": [
        "home.banner",
        "home.brand-marque",
        "home.aura-section",
        "home.intro-section",
        "home.our-portfolio",
        "home.industries-section",
        "home.awards-section",
        "common.testimonial-section",
        "common.header",
        "common.footer",
        "blog.blog-listing",
        "blog.pluse-listing",
        "about.vision-section",
        "about.team-member",
        "about.our-team",
        "about.leader-section",
        "about.intro-section",
        "about.banner-section",
        "about.about-note",
        "contact.headquarters",
        "contact.find-us",
        "contact.banner-form",
        "career.career-info"
      ]
    }
  }
}
